polars_coord_transforms-0.12.1.dist-info/METADATA
polars_coord_transforms-0.12.1.dist-info/WHEEL
polars_coord_transforms-0.12.1.dist-info/licenses/LICENSE
polars_coord_transforms/py.typed
polars_coord_transforms/__init__.py
polars_coord_transforms/polars_coord_transforms.cpython-310-aarch64-linux-gnu.so
polars_coord_transforms-0.12.1.dist-info/RECORD
