Metadata-Version: 2.4
Name: polars-coord-transforms
Version: 0.12.1
Classifier: Programming Language :: Rust
Classifier: Programming Language :: Python :: Implementation :: CPython
Classifier: Programming Language :: Python :: Implementation :: PyPy
Requires-Dist: polars >=0.20.0
License-File: LICENSE
Summary: Tools for coordinate transforms and S2-indexing via Polars Expression Plugins
Author: Georgy Popov
Requires-Python: >=3.8
Project-URL: Homepage, https://github.com/georgypv/polars-coord-transforms/
